matb.py
matb-0.0.1.dist-info/WHEEL
matb-0.0.1.dist-info/METADATA
matb-0.0.1.dist-info/RECORD
