Metadata-Version: 2.1
Name: matb
Version: 0.0.1
Summary: Matb sdohla
Author: Otchim tvoi
Requires-Python: >=3.8,<4.0
Classifier: Programming Language :: Python :: 3
Classifier: Programming Language :: Python :: 3.8
Classifier: Programming Language :: Python :: 3.9
